[
  {
    "url": "https://api.github.com/repos/ThatCoders/thatcoders.github.io/issues/21",
    "repository_url": "https://api.github.com/repos/ThatCoders/thatcoders.github.io",
    "labels_url": "https://api.github.com/repos/ThatCoders/thatcoders.github.io/issues/21/labels{/name}",
    "comments_url": "https://api.github.com/repos/ThatCoders/thatcoders.github.io/issues/21/comments",
    "events_url": "https://api.github.com/repos/ThatCoders/thatcoders.github.io/issues/21/events",
    "html_url": "https://github.com/ThatCoders/thatcoders.github.io/issues/21",
    "id": 1650959827,
    "node_id": "I_kwDOIbr2Q85iZ6XT",
    "number": 21,
    "title": "网站故障",
    "user": {
      "login": "ThatCoders",
      "id": 43780818,
      "node_id": "MDQ6VXNlcjQzNzgwODE4",
      "avatar_url": "https://avatars.githubusercontent.com/u/43780818?v=4",
      "gravatar_id": "",
      "url": "https://api.github.com/users/ThatCoders",
      "html_url": "https://github.com/ThatCoders",
      "followers_url": "https://api.github.com/users/ThatCoders/followers",
      "following_url": "https://api.github.com/users/ThatCoders/following{/other_user}",
      "gists_url": "https://api.github.com/users/ThatCoders/gists{/gist_id}",
      "starred_url": "https://api.github.com/users/ThatCoders/starred{/owner}{/repo}",
      "subscriptions_url": "https://api.github.com/users/ThatCoders/subscriptions",
      "organizations_url": "https://api.github.com/users/ThatCoders/orgs",
      "repos_url": "https://api.github.com/users/ThatCoders/repos",
      "events_url": "https://api.github.com/users/ThatCoders/events{/privacy}",
      "received_events_url": "https://api.github.com/users/ThatCoders/received_events",
      "type": "User",
      "site_admin": false
    },
    "labels": [
      {
        "id": 5016963839,
        "node_id": "LA_kwDOIbr2Q88AAAABKwjK_w",
        "url": "https://api.github.com/repos/ThatCoders/thatcoders.github.io/labels/Chat",
        "name": "Chat",
        "color": "f78ca0",
        "default": false,
        "description": "作者专属动态标签"
      }
    ],
    "state": "open",
    "locked": false,
    "assignee": null,
    "assignees": [],
    "milestone": null,
    "comments": 0,
    "created_at": "2023-04-02T14:02:15Z",
    "updated_at": "2023-04-02T14:02:15Z",
    "closed_at": null,
    "author_association": "OWNER",
    "active_lock_reason": null,
    "body": "服务器的80/443端口被封, 博客的某些功能可能有问题, 例如评论等。\r\n有空再解决吧......",
    "reactions": {
      "url": "https://api.github.com/repos/ThatCoders/thatcoders.github.io/issues/21/reactions",
      "total_count": 0,
      "+1": 0,
      "-1": 0,
      "laugh": 0,
      "hooray": 0,
      "confused": 0,
      "heart": 0,
      "rocket": 0,
      "eyes": 0
    },
    "timeline_url": "https://api.github.com/repos/ThatCoders/thatcoders.github.io/issues/21/timeline",
    "performed_via_github_app": null,
    "state_reason": null
  },
  {
    "url": "https://api.github.com/repos/ThatCoders/thatcoders.github.io/issues/20",
    "repository_url": "https://api.github.com/repos/ThatCoders/thatcoders.github.io",
    "labels_url": "https://api.github.com/repos/ThatCoders/thatcoders.github.io/issues/20/labels{/name}",
    "comments_url": "https://api.github.com/repos/ThatCoders/thatcoders.github.io/issues/20/comments",
    "events_url": "https://api.github.com/repos/ThatCoders/thatcoders.github.io/issues/20/events",
    "html_url": "https://github.com/ThatCoders/thatcoders.github.io/issues/20",
    "id": 1609644762,
    "node_id": "I_kwDOIbr2Q85f8Tra",
    "number": 20,
    "title": "我不干了",
    "user": {
      "login": "ThatCoders",
      "id": 43780818,
      "node_id": "MDQ6VXNlcjQzNzgwODE4",
      "avatar_url": "https://avatars.githubusercontent.com/u/43780818?v=4",
      "gravatar_id": "",
      "url": "https://api.github.com/users/ThatCoders",
      "html_url": "https://github.com/ThatCoders",
      "followers_url": "https://api.github.com/users/ThatCoders/followers",
      "following_url": "https://api.github.com/users/ThatCoders/following{/other_user}",
      "gists_url": "https://api.github.com/users/ThatCoders/gists{/gist_id}",
      "starred_url": "https://api.github.com/users/ThatCoders/starred{/owner}{/repo}",
      "subscriptions_url": "https://api.github.com/users/ThatCoders/subscriptions",
      "organizations_url": "https://api.github.com/users/ThatCoders/orgs",
      "repos_url": "https://api.github.com/users/ThatCoders/repos",
      "events_url": "https://api.github.com/users/ThatCoders/events{/privacy}",
      "received_events_url": "https://api.github.com/users/ThatCoders/received_events",
      "type": "User",
      "site_admin": false
    },
    "labels": [
      {
        "id": 5016963839,
        "node_id": "LA_kwDOIbr2Q88AAAABKwjK_w",
        "url": "https://api.github.com/repos/ThatCoders/thatcoders.github.io/labels/Chat",
        "name": "Chat",
        "color": "f78ca0",
        "default": false,
        "description": "作者专属动态标签"
      }
    ],
    "state": "open",
    "locked": false,
    "assignee": null,
    "assignees": [],
    "milestone": null,
    "comments": 0,
    "created_at": "2023-03-04T06:53:19Z",
    "updated_at": "2023-03-04T06:53:57Z",
    "closed_at": null,
    "author_association": "OWNER",
    "active_lock_reason": null,
    "body": "写单写累了, 写完手头上的4月开始不接, 给别人写代码真心累. \r\n![bb_slap](https://blog.thatcoder.cn/custom/package/waline/emoji/bilibili/bb_slap.png)",
    "reactions": {
      "url": "https://api.github.com/repos/ThatCoders/thatcoders.github.io/issues/20/reactions",
      "total_count": 0,
      "+1": 0,
      "-1": 0,
      "laugh": 0,
      "hooray": 0,
      "confused": 0,
      "heart": 0,
      "rocket": 0,
      "eyes": 0
    },
    "timeline_url": "https://api.github.com/repos/ThatCoders/thatcoders.github.io/issues/20/timeline",
    "performed_via_github_app": null,
    "state_reason": null
  },
  {
    "url": "https://api.github.com/repos/ThatCoders/thatcoders.github.io/issues/19",
    "repository_url": "https://api.github.com/repos/ThatCoders/thatcoders.github.io",
    "labels_url": "https://api.github.com/repos/ThatCoders/thatcoders.github.io/issues/19/labels{/name}",
    "comments_url": "https://api.github.com/repos/ThatCoders/thatcoders.github.io/issues/19/comments",
    "events_url": "https://api.github.com/repos/ThatCoders/thatcoders.github.io/issues/19/events",
    "html_url": "https://github.com/ThatCoders/thatcoders.github.io/issues/19",
    "id": 1579357109,
    "node_id": "I_kwDOIbr2Q85eIxO1",
    "number": 19,
    "title": "博客进入缓慢更新",
    "user": {
      "login": "ThatCoders",
      "id": 43780818,
      "node_id": "MDQ6VXNlcjQzNzgwODE4",
      "avatar_url": "https://avatars.githubusercontent.com/u/43780818?v=4",
      "gravatar_id": "",
      "url": "https://api.github.com/users/ThatCoders",
      "html_url": "https://github.com/ThatCoders",
      "followers_url": "https://api.github.com/users/ThatCoders/followers",
      "following_url": "https://api.github.com/users/ThatCoders/following{/other_user}",
      "gists_url": "https://api.github.com/users/ThatCoders/gists{/gist_id}",
      "starred_url": "https://api.github.com/users/ThatCoders/starred{/owner}{/repo}",
      "subscriptions_url": "https://api.github.com/users/ThatCoders/subscriptions",
      "organizations_url": "https://api.github.com/users/ThatCoders/orgs",
      "repos_url": "https://api.github.com/users/ThatCoders/repos",
      "events_url": "https://api.github.com/users/ThatCoders/events{/privacy}",
      "received_events_url": "https://api.github.com/users/ThatCoders/received_events",
      "type": "User",
      "site_admin": false
    },
    "labels": [
      {
        "id": 5016963839,
        "node_id": "LA_kwDOIbr2Q88AAAABKwjK_w",
        "url": "https://api.github.com/repos/ThatCoders/thatcoders.github.io/labels/Chat",
        "name": "Chat",
        "color": "f78ca0",
        "default": false,
        "description": "作者专属动态标签"
      }
    ],
    "state": "open",
    "locked": false,
    "assignee": null,
    "assignees": [],
    "milestone": null,
    "comments": 0,
    "created_at": "2023-02-10T09:42:25Z",
    "updated_at": "2023-02-10T09:42:25Z",
    "closed_at": null,
    "author_association": "OWNER",
    "active_lock_reason": null,
    "body": "开学才想起来我是个后端, 得开始学习了.\r\n博客会进入缓慢更新阶段.",
    "reactions": {
      "url": "https://api.github.com/repos/ThatCoders/thatcoders.github.io/issues/19/reactions",
      "total_count": 0,
      "+1": 0,
      "-1": 0,
      "laugh": 0,
      "hooray": 0,
      "confused": 0,
      "heart": 0,
      "rocket": 0,
      "eyes": 0
    },
    "timeline_url": "https://api.github.com/repos/ThatCoders/thatcoders.github.io/issues/19/timeline",
    "performed_via_github_app": null,
    "state_reason": null
  },
  {
    "url": "https://api.github.com/repos/ThatCoders/thatcoders.github.io/issues/18",
    "repository_url": "https://api.github.com/repos/ThatCoders/thatcoders.github.io",
    "labels_url": "https://api.github.com/repos/ThatCoders/thatcoders.github.io/issues/18/labels{/name}",
    "comments_url": "https://api.github.com/repos/ThatCoders/thatcoders.github.io/issues/18/comments",
    "events_url": "https://api.github.com/repos/ThatCoders/thatcoders.github.io/issues/18/events",
    "html_url": "https://github.com/ThatCoders/thatcoders.github.io/issues/18",
    "id": 1570197867,
    "node_id": "I_kwDOIbr2Q85dl1Fr",
    "number": 18,
    "title": "网站1月份翻新",
    "user": {
      "login": "ThatCoders",
      "id": 43780818,
      "node_id": "MDQ6VXNlcjQzNzgwODE4",
      "avatar_url": "https://avatars.githubusercontent.com/u/43780818?v=4",
      "gravatar_id": "",
      "url": "https://api.github.com/users/ThatCoders",
      "html_url": "https://github.com/ThatCoders",
      "followers_url": "https://api.github.com/users/ThatCoders/followers",
      "following_url": "https://api.github.com/users/ThatCoders/following{/other_user}",
      "gists_url": "https://api.github.com/users/ThatCoders/gists{/gist_id}",
      "starred_url": "https://api.github.com/users/ThatCoders/starred{/owner}{/repo}",
      "subscriptions_url": "https://api.github.com/users/ThatCoders/subscriptions",
      "organizations_url": "https://api.github.com/users/ThatCoders/orgs",
      "repos_url": "https://api.github.com/users/ThatCoders/repos",
      "events_url": "https://api.github.com/users/ThatCoders/events{/privacy}",
      "received_events_url": "https://api.github.com/users/ThatCoders/received_events",
      "type": "User",
      "site_admin": false
    },
    "labels": [
      {
        "id": 5016963839,
        "node_id": "LA_kwDOIbr2Q88AAAABKwjK_w",
        "url": "https://api.github.com/repos/ThatCoders/thatcoders.github.io/labels/Chat",
        "name": "Chat",
        "color": "f78ca0",
        "default": false,
        "description": "作者专属动态标签"
      }
    ],
    "state": "open",
    "locked": false,
    "assignee": null,
    "assignees": [],
    "milestone": null,
    "comments": 0,
    "created_at": "2023-02-03T17:26:26Z",
    "updated_at": "2023-02-03T17:26:26Z",
    "closed_at": null,
    "author_association": "OWNER",
    "active_lock_reason": null,
    "body": "- 添加不蒜子统计\r\n- 添加可控制昼夜\r\n- 添加代码块复制\r\n- 修改代码块样式\r\n- 修改文章目录样式",
    "reactions": {
      "url": "https://api.github.com/repos/ThatCoders/thatcoders.github.io/issues/18/reactions",
      "total_count": 0,
      "+1": 0,
      "-1": 0,
      "laugh": 0,
      "hooray": 0,
      "confused": 0,
      "heart": 0,
      "rocket": 0,
      "eyes": 0
    },
    "timeline_url": "https://api.github.com/repos/ThatCoders/thatcoders.github.io/issues/18/timeline",
    "performed_via_github_app": null,
    "state_reason": null
  },
  {
    "url": "https://api.github.com/repos/ThatCoders/thatcoders.github.io/issues/14",
    "repository_url": "https://api.github.com/repos/ThatCoders/thatcoders.github.io",
    "labels_url": "https://api.github.com/repos/ThatCoders/thatcoders.github.io/issues/14/labels{/name}",
    "comments_url": "https://api.github.com/repos/ThatCoders/thatcoders.github.io/issues/14/comments",
    "events_url": "https://api.github.com/repos/ThatCoders/thatcoders.github.io/issues/14/events",
    "html_url": "https://github.com/ThatCoders/thatcoders.github.io/issues/14",
    "id": 1552112363,
    "node_id": "I_kwDOIbr2Q85cg1rr",
    "number": 14,
    "title": "新年快乐!",
    "user": {
      "login": "ThatCoders",
      "id": 43780818,
      "node_id": "MDQ6VXNlcjQzNzgwODE4",
      "avatar_url": "https://avatars.githubusercontent.com/u/43780818?v=4",
      "gravatar_id": "",
      "url": "https://api.github.com/users/ThatCoders",
      "html_url": "https://github.com/ThatCoders",
      "followers_url": "https://api.github.com/users/ThatCoders/followers",
      "following_url": "https://api.github.com/users/ThatCoders/following{/other_user}",
      "gists_url": "https://api.github.com/users/ThatCoders/gists{/gist_id}",
      "starred_url": "https://api.github.com/users/ThatCoders/starred{/owner}{/repo}",
      "subscriptions_url": "https://api.github.com/users/ThatCoders/subscriptions",
      "organizations_url": "https://api.github.com/users/ThatCoders/orgs",
      "repos_url": "https://api.github.com/users/ThatCoders/repos",
      "events_url": "https://api.github.com/users/ThatCoders/events{/privacy}",
      "received_events_url": "https://api.github.com/users/ThatCoders/received_events",
      "type": "User",
      "site_admin": false
    },
    "labels": [
      {
        "id": 5016963839,
        "node_id": "LA_kwDOIbr2Q88AAAABKwjK_w",
        "url": "https://api.github.com/repos/ThatCoders/thatcoders.github.io/labels/Chat",
        "name": "Chat",
        "color": "f78ca0",
        "default": false,
        "description": "作者专属动态标签"
      }
    ],
    "state": "open",
    "locked": false,
    "assignee": null,
    "assignees": [],
    "milestone": null,
    "comments": 0,
    "created_at": "2023-01-22T13:15:01Z",
    "updated_at": "2023-01-29T04:52:22Z",
    "closed_at": null,
    "author_association": "OWNER",
    "active_lock_reason": null,
    "body": "![](https://cdn.seclusion.work/myself/typora/202301222113880.png)",
    "reactions": {
      "url": "https://api.github.com/repos/ThatCoders/thatcoders.github.io/issues/14/reactions",
      "total_count": 0,
      "+1": 0,
      "-1": 0,
      "laugh": 0,
      "hooray": 0,
      "confused": 0,
      "heart": 0,
      "rocket": 0,
      "eyes": 0
    },
    "timeline_url": "https://api.github.com/repos/ThatCoders/thatcoders.github.io/issues/14/timeline",
    "performed_via_github_app": null,
    "state_reason": null
  },
  {
    "url": "https://api.github.com/repos/ThatCoders/thatcoders.github.io/issues/10",
    "repository_url": "https://api.github.com/repos/ThatCoders/thatcoders.github.io",
    "labels_url": "https://api.github.com/repos/ThatCoders/thatcoders.github.io/issues/10/labels{/name}",
    "comments_url": "https://api.github.com/repos/ThatCoders/thatcoders.github.io/issues/10/comments",
    "events_url": "https://api.github.com/repos/ThatCoders/thatcoders.github.io/issues/10/events",
    "html_url": "https://github.com/ThatCoders/thatcoders.github.io/issues/10",
    "id": 1548359923,
    "node_id": "I_kwDOIbr2Q85cShjz",
    "number": 10,
    "title": "wordpress转hexo",
    "user": {
      "login": "ThatCoders",
      "id": 43780818,
      "node_id": "MDQ6VXNlcjQzNzgwODE4",
      "avatar_url": "https://avatars.githubusercontent.com/u/43780818?v=4",
      "gravatar_id": "",
      "url": "https://api.github.com/users/ThatCoders",
      "html_url": "https://github.com/ThatCoders",
      "followers_url": "https://api.github.com/users/ThatCoders/followers",
      "following_url": "https://api.github.com/users/ThatCoders/following{/other_user}",
      "gists_url": "https://api.github.com/users/ThatCoders/gists{/gist_id}",
      "starred_url": "https://api.github.com/users/ThatCoders/starred{/owner}{/repo}",
      "subscriptions_url": "https://api.github.com/users/ThatCoders/subscriptions",
      "organizations_url": "https://api.github.com/users/ThatCoders/orgs",
      "repos_url": "https://api.github.com/users/ThatCoders/repos",
      "events_url": "https://api.github.com/users/ThatCoders/events{/privacy}",
      "received_events_url": "https://api.github.com/users/ThatCoders/received_events",
      "type": "User",
      "site_admin": false
    },
    "labels": [
      {
        "id": 5016963839,
        "node_id": "LA_kwDOIbr2Q88AAAABKwjK_w",
        "url": "https://api.github.com/repos/ThatCoders/thatcoders.github.io/labels/Chat",
        "name": "Chat",
        "color": "f78ca0",
        "default": false,
        "description": "作者专属动态标签"
      }
    ],
    "state": "open",
    "locked": false,
    "assignee": null,
    "assignees": [],
    "milestone": null,
    "comments": 0,
    "created_at": "2023-01-19T01:02:53Z",
    "updated_at": "2023-01-19T01:03:02Z",
    "closed_at": null,
    "author_association": "OWNER",
    "active_lock_reason": null,
    "body": "近期会慢慢把文章搬到这个网站, 逃离PHP, 前路漫漫且艰辛。\r\n![wp](https://user-images.githubusercontent.com/43780818/213331240-67b2ac2e-2104-48f5-adf1-5db7ff9f88d1.png)\r\n",
    "reactions": {
      "url": "https://api.github.com/repos/ThatCoders/thatcoders.github.io/issues/10/reactions",
      "total_count": 1,
      "+1": 0,
      "-1": 0,
      "laugh": 0,
      "hooray": 0,
      "confused": 0,
      "heart": 0,
      "rocket": 1,
      "eyes": 0
    },
    "timeline_url": "https://api.github.com/repos/ThatCoders/thatcoders.github.io/issues/10/timeline",
    "performed_via_github_app": null,
    "state_reason": null
  },
  {
    "url": "https://api.github.com/repos/ThatCoders/thatcoders.github.io/issues/8",
    "repository_url": "https://api.github.com/repos/ThatCoders/thatcoders.github.io",
    "labels_url": "https://api.github.com/repos/ThatCoders/thatcoders.github.io/issues/8/labels{/name}",
    "comments_url": "https://api.github.com/repos/ThatCoders/thatcoders.github.io/issues/8/comments",
    "events_url": "https://api.github.com/repos/ThatCoders/thatcoders.github.io/issues/8/events",
    "html_url": "https://github.com/ThatCoders/thatcoders.github.io/issues/8",
    "id": 1538639059,
    "node_id": "I_kwDOIbr2Q85btcTT",
    "number": 8,
    "title": "动态测试",
    "user": {
      "login": "ThatCoders",
      "id": 43780818,
      "node_id": "MDQ6VXNlcjQzNzgwODE4",
      "avatar_url": "https://avatars.githubusercontent.com/u/43780818?v=4",
      "gravatar_id": "",
      "url": "https://api.github.com/users/ThatCoders",
      "html_url": "https://github.com/ThatCoders",
      "followers_url": "https://api.github.com/users/ThatCoders/followers",
      "following_url": "https://api.github.com/users/ThatCoders/following{/other_user}",
      "gists_url": "https://api.github.com/users/ThatCoders/gists{/gist_id}",
      "starred_url": "https://api.github.com/users/ThatCoders/starred{/owner}{/repo}",
      "subscriptions_url": "https://api.github.com/users/ThatCoders/subscriptions",
      "organizations_url": "https://api.github.com/users/ThatCoders/orgs",
      "repos_url": "https://api.github.com/users/ThatCoders/repos",
      "events_url": "https://api.github.com/users/ThatCoders/events{/privacy}",
      "received_events_url": "https://api.github.com/users/ThatCoders/received_events",
      "type": "User",
      "site_admin": false
    },
    "labels": [
      {
        "id": 5016963839,
        "node_id": "LA_kwDOIbr2Q88AAAABKwjK_w",
        "url": "https://api.github.com/repos/ThatCoders/thatcoders.github.io/labels/Chat",
        "name": "Chat",
        "color": "f78ca0",
        "default": false,
        "description": "作者专属动态标签"
      }
    ],
    "state": "open",
    "locked": false,
    "assignee": null,
    "assignees": [],
    "milestone": null,
    "comments": 0,
    "created_at": "2023-01-18T20:07:18Z",
    "updated_at": "2023-02-15T09:18:35Z",
    "closed_at": null,
    "author_association": "OWNER",
    "active_lock_reason": null,
    "body": "![download](https://user-images.githubusercontent.com/43780818/213283582-2ae71837-c89d-4f41-abc6-0de9d447c638.png)\r\n",
    "reactions": {
      "url": "https://api.github.com/repos/ThatCoders/thatcoders.github.io/issues/8/reactions",
      "total_count": 2,
      "+1": 0,
      "-1": 0,
      "laugh": 0,
      "hooray": 2,
      "confused": 0,
      "heart": 0,
      "rocket": 0,
      "eyes": 0
    },
    "timeline_url": "https://api.github.com/repos/ThatCoders/thatcoders.github.io/issues/8/timeline",
    "performed_via_github_app": null,
    "state_reason": null
  },
  {
    "url": "https://api.github.com/repos/ThatCoders/thatcoders.github.io/issues/2",
    "repository_url": "https://api.github.com/repos/ThatCoders/thatcoders.github.io",
    "labels_url": "https://api.github.com/repos/ThatCoders/thatcoders.github.io/issues/2/labels{/name}",
    "comments_url": "https://api.github.com/repos/ThatCoders/thatcoders.github.io/issues/2/comments",
    "events_url": "https://api.github.com/repos/ThatCoders/thatcoders.github.io/issues/2/events",
    "html_url": "https://github.com/ThatCoders/thatcoders.github.io/issues/2",
    "id": 1536719986,
    "node_id": "I_kwDOIbr2Q85bmHxy",
    "number": 2,
    "title": "第二次使用stellar",
    "user": {
      "login": "ThatCoders",
      "id": 43780818,
      "node_id": "MDQ6VXNlcjQzNzgwODE4",
      "avatar_url": "https://avatars.githubusercontent.com/u/43780818?v=4",
      "gravatar_id": "",
      "url": "https://api.github.com/users/ThatCoders",
      "html_url": "https://github.com/ThatCoders",
      "followers_url": "https://api.github.com/users/ThatCoders/followers",
      "following_url": "https://api.github.com/users/ThatCoders/following{/other_user}",
      "gists_url": "https://api.github.com/users/ThatCoders/gists{/gist_id}",
      "starred_url": "https://api.github.com/users/ThatCoders/starred{/owner}{/repo}",
      "subscriptions_url": "https://api.github.com/users/ThatCoders/subscriptions",
      "organizations_url": "https://api.github.com/users/ThatCoders/orgs",
      "repos_url": "https://api.github.com/users/ThatCoders/repos",
      "events_url": "https://api.github.com/users/ThatCoders/events{/privacy}",
      "received_events_url": "https://api.github.com/users/ThatCoders/received_events",
      "type": "User",
      "site_admin": false
    },
    "labels": [
      {
        "id": 5016963839,
        "node_id": "LA_kwDOIbr2Q88AAAABKwjK_w",
        "url": "https://api.github.com/repos/ThatCoders/thatcoders.github.io/labels/Chat",
        "name": "Chat",
        "color": "f78ca0",
        "default": false,
        "description": "作者专属动态标签"
      }
    ],
    "state": "open",
    "locked": false,
    "assignee": null,
    "assignees": [],
    "milestone": null,
    "comments": 0,
    "created_at": "2023-01-17T16:54:48Z",
    "updated_at": "2023-01-18T20:15:41Z",
    "closed_at": null,
    "author_association": "OWNER",
    "active_lock_reason": null,
    "body": "第二次使用stellar, 有一种回家的感觉, 同时stellar已经更新的非常完善了。",
    "reactions": {
      "url": "https://api.github.com/repos/ThatCoders/thatcoders.github.io/issues/2/reactions",
      "total_count": 0,
      "+1": 0,
      "-1": 0,
      "laugh": 0,
      "hooray": 0,
      "confused": 0,
      "heart": 0,
      "rocket": 0,
      "eyes": 0
    },
    "timeline_url": "https://api.github.com/repos/ThatCoders/thatcoders.github.io/issues/2/timeline",
    "performed_via_github_app": null,
    "state_reason": null
  }
]